setup.py
statdials/__init__.py
statdials/statdials.sty
statdials.egg-info/PKG-INFO
statdials.egg-info/SOURCES.txt
statdials.egg-info/dependency_links.txt
statdials.egg-info/not-zip-safe
statdials.egg-info/requires.txt
statdials.egg-info/top_level.txt