Metadata-Version: 1.1
Name: statdials
Version: 0.1.1
Summary: LaTeX and Python library to create cute graphical metric dials.
Home-page: UNKNOWN
Author: Matthew Wardrop
Author-email: mister.wardrop@gmail.com
License: UNKNOWN
Platform: UNKNOWN
Classifier: Development Status :: 2 - Pre-Alpha
Classifier: Environment :: Console
Classifier: Intended Audience :: Developers
Classifier: Intended Audience :: Information Technology
Classifier: Intended Audience :: Science/Research
Classifier: License :: OSI Approved :: MIT License
Classifier: Programming Language :: Python :: 2.7
Classifier: Programming Language :: Python :: 3.5
Classifier: Programming Language :: Python :: 3.6
